mseep_frankfurtermcp-0.3.2.dist-info/licenses/LICENSE
tests/__init__.py
tests/test_composition.py
tests/test_server.py
mseep_frankfurtermcp-0.3.2.dist-info/METADATA
mseep_frankfurtermcp-0.3.2.dist-info/WHEEL
mseep_frankfurtermcp-0.3.2.dist-info/top_level.txt
mseep_frankfurtermcp-0.3.2.dist-info/RECORD
