Metadata-Version: 2.4
Name: mseep-frankfurtermcp
Version: 0.3.2
Summary: A MCP server for currency exchange rates and currency conversion using the Frankfurter API.
Home-page: https://github.com/mseep
Author: mseep
Author-email: support@skydeck.ai
Maintainer: mseep
Maintainer-email: support@skydeck.ai
Keywords: mseep,finance,mcp,currency-exchange-rates,currency-converter,frankfurter-api,model-context-protocol,mcp-server,fastmcp,model-context-protocol-server,mcp-composition
Classifier: Programming Language :: Python :: 3
Classifier: License :: OSI Approved :: MIT License
Classifier: Operating System :: OS Independent
Requires-Python: >=3.6
License-File: LICENSE
Requires-Dist: fastmcp>=2.8.0
Requires-Dist: python-dotenv>=1.1.0
Requires-Dist: typer>=0.16.0
Dynamic: author
Dynamic: author-email
Dynamic: classifier
Dynamic: description
Dynamic: description-content-type
Dynamic: home-page
Dynamic: keywords
Dynamic: license-file
Dynamic: maintainer
Dynamic: maintainer-email
Dynamic: requires-dist
Dynamic: requires-python
Dynamic: summary
